calltracing/__init__.py
calltracing/call_context.py
calltracing-1.0.1.dist-info/LICENSE
calltracing-1.0.1.dist-info/METADATA
calltracing-1.0.1.dist-info/WHEEL
calltracing-1.0.1.dist-info/RECORD
