Metadata-Version: 2.3
Name: calltracing
Version: 1.0.1
Summary: Minimalistic lib for trace calls
License: MIT
Keywords: trace,calls,lib,sync,inspect
Author: anybody
Requires-Python: >=3.11,<4.0
Classifier: Development Status :: 5 - Production/Stable
Classifier: Intended Audience :: Developers
Classifier: License :: OSI Approved :: MIT License
Classifier: Programming Language :: Python :: 3
Classifier: Programming Language :: Python :: 3.11
Classifier: Programming Language :: Python :: 3.12
Classifier: Programming Language :: Python :: 3.13
Classifier: Topic :: Communications :: Chat
Classifier: Topic :: Software Development :: Libraries :: Application Frameworks
Classifier: Typing :: Typed
Project-URL: Documentation, https://github.com/user_with_username/calltracer/
Project-URL: Homepage, https://github.com/user_with_username/calltracer
Project-URL: Repository, https://github.com/user_with_username/calltracer
